[{"src":"https://www.clien.net/service/board/park/14699854?type=recommend","title":"대통령 욕하는 동창 손절했어요","view_num":36947,"comment_num":209,"post_time":"2020-03-12 05:58:30","thumbnail":null},{"src":"https://www.clien.net/service/board/park/14699856?type=recommend","title":"퇴사 하러 다녀온 뒷 이야기입니다(직장 괴롭힘 해결).","view_num":33977,"comment_num":87,"post_time":"2020-03-12 05:58:55","thumbnail":null},{"src":"https://www.clien.net/service/board/park/14699852?type=recommend","title":"드디어 BBC 뉴스채널에서도 한국 칭찬 보도하는군요","view_num":31241,"comment_num":62,"post_time":"2020-03-12 05:56:34","thumbnail":null},{"src":"https://www.clien.net/service/board/park/14699936?type=recommend","title":"권영진 기자회견 어설픈 타짜.jpg(보배)","view_num":31581,"comment_num":58,"post_time":"2020-03-12 07:23:35","thumbnail":{"src":"https://cdn.clien.net/web/api/file/F01/9737006/1a9ca7530ea973.jpg?w=780&h=30000","size":{"width":780,"height":3683}}},{"src":"https://www.clien.net/service/board/park/14699815?type=recommend","title":"bbc 로라 비커 님 근황","view_num":30271,"comment_num":19,"post_time":"2020-03-12 04:31:27","thumbnail":null},{"src":"https://www.clien.net/service/board/park/14699823?type=recommend","title":"외국인 교수의 시각","view_num":26002,"comment_num":39,"post_time":"2020-03-12 04:43:03","thumbnail":null},{"src":"https://www.clien.net/service/board/park/14699988?type=recommend","title":"왜 손정의가 욕을 먹을까? 일본인의 사고방식","view_num":18225,"comment_num":56,"post_time":"2020-03-12 07:42:57","thumbnail":null},{"src":"https://www.clien.net/service/board/park/14700296?type=recommend","title":"후임이 취향인데 어떻게하죠","view_num":13307,"comment_num":74,"post_time":"2020-03-12 09:28:06","thumbnail":{"src":"https://cdn.clien.net/web/api/file/F01/9737423/1aa3b3cdda6cff.png?w=780&h=30000&gif=true","size":{"width":366,"height":174}}},{"src":"https://www.clien.net/service/board/park/14700006?type=recommend","title":"비례정당 여론조사","view_num":14105,"comment_num":54,"post_time":"2020-03-12 07:52:57","thumbnail":{"src":"https://cdn.clien.net/web/api/file/F01/9737061/1a9e2fd857b124.jpg?w=780&h=30000","size":{"width":400,"height":720}}},{"src":"https://www.clien.net/service/board/park/14700240?type=recommend","title":"이정미 의원이 롤대리 문제를 가볍게 보는 듯 하는데..","view_num":9935,"comment_num":62,"post_time":"2020-03-12 09:13:23","thumbnail":null},{"src":"https://www.clien.net/service/board/park/14700258?type=recommend","title":"2020년대 고속버스 터미널","view_num":18638,"comment_num":44,"post_time":"2020-03-12 09:18:33","thumbnail":{"src":"https://cdn.clien.net/web/api/file/F01/9737326/1aa2d98c804a32.jpg?w=780&h=30000","size":{"width":780,"height":1041}}},{"src":"https://www.clien.net/service/board/park/14700162?type=recommend","title":"펑했습니다","view_num":10224,"comment_num":36,"post_time":"2020-03-12 08:48:10","thumbnail":null},{"src":"https://www.clien.net/service/board/park/14699984?type=recommend","title":"뉴스공장 개성공단의 봉제, 마스크, 방호복 공장만 가동해도","view_num":6872,"comment_num":53,"post_time":"2020-03-12 07:42:04","thumbnail":null},{"src":"https://www.clien.net/service/board/park/14699870?type=recommend","title":"조선일보 미주 일면...","view_num":9246,"comment_num":29,"post_time":"2020-03-12 06:25:00","thumbnail":{"src":"https://cdn.clien.net/web/api/file/F01/9736938/1a996eba411829.jpg?w=780&h=30000&gif=true","size":{"width":780,"height":585}}},{"src":"https://www.clien.net/service/board/park/14700191?type=recommend","title":"미국의회 '한국처럼 왜 못하나'","view_num":7670,"comment_num":27,"post_time":"2020-03-12 08:57:29","thumbnail":{"src":"https://cdn.clien.net/web/api/file/F01/9737263/1aa1a25f8aa9c6.jpg?w=780&h=30000","size":{"width":780,"height":2179}}},{"src":"https://www.clien.net/service/board/park/14700214?type=recommend","title":"열린민주당 8.3% 나왔지만","view_num":7214,"comment_num":29,"post_time":"2020-03-12 09:06:26","thumbnail":null},{"src":"https://www.clien.net/service/board/park/14700062?type=recommend","title":"오마이뉴스-리얼미터로 계산한 비례대표 의석수","view_num":6787,"comment_num":30,"post_time":"2020-03-12 08:15:17","thumbnail":{"src":"https://imgnews.pstatic.net/image/047/2020/03/12/0002260886_002_20200312073605717.jpg?type=w430","size":{"width":400,"height":720}}},{"src":"https://www.clien.net/service/board/park/14700151?type=recommend","title":"와!! 사나!!!!!???........","view_num":19146,"comment_num":16,"post_time":"2020-03-12 08:45:05","thumbnail":{"src":"https://cdn.clien.net/web/api/file/F01/9737222/1aa0e710d960b3.jpg?w=780&h=30000&gif=true","size":{"width":300,"height":168}}},{"src":"https://www.clien.net/service/board/park/14700037?type=recommend","title":"월간조선이 다급히 내린 기사?! 사실인가요?","view_num":10106,"comment_num":12,"post_time":"2020-03-12 08:05:34","thumbnail":{"src":"https://cdn.clien.net/web/api/file/F01/9737110/1a9ee3a950b75c.jpg?w=780&h=30000","size":{"width":670,"height":967}}},{"src":"https://www.clien.net/service/board/park/14699989?type=recommend","title":"울컥하네요..유재석 ㅠㅠ","view_num":10598,"comment_num":8,"post_time":"2020-03-12 07:44:48","thumbnail":{"src":"https://cdn.clien.net/web/api/file/F01/9737052/1a9dc508a0913d.jpg?w=780&h=30000","size":{"width":780,"height":369}}},{"src":"https://www.clien.net/service/board/park/14700206?type=recommend","title":"회사 외국 사람들이 한국에 있고 싶어 합니다.","view_num":6910,"comment_num":24,"post_time":"2020-03-12 09:03:41","thumbnail":null},{"src":"https://www.clien.net/service/board/park/14699829?type=recommend","title":"미국 코로나 바이러스 근황","view_num":9460,"comment_num":9,"post_time":"2020-03-12 04:59:47","thumbnail":null},{"src":"https://www.clien.net/service/board/park/14699996?type=recommend","title":"미국내 코로나 상황이 개판된 이유","view_num":9247,"comment_num":9,"post_time":"2020-03-12 07:49:43","thumbnail":null},{"src":"https://www.clien.net/service/board/park/14699944?type=recommend","title":"장제원 공직자 자격 없..","view_num":8524,"comment_num":9,"post_time":"2020-03-12 07:26:16","thumbnail":{"src":"https://cdn.clien.net/web/api/file/F01/9737012/1a9ccd4cde2dcb.jpeg?w=780&h=30000","size":{"width":461,"height":512}}},{"src":"https://www.clien.net/service/board/park/14700301?type=recommend","title":"나이키 설현신발 품절","view_num":13599,"comment_num":24,"post_time":"2020-03-12 09:29:08","thumbnail":{"src":"https://cdn.clien.net/web/api/file/F01/9737394/1aa3725160aa39.jpg?w=780&h=30000","size":{"width":780,"height":1603}}},{"src":"https://www.clien.net/service/board/park/14700343?type=recommend","title":"벌교터미널","view_num":9658,"comment_num":25,"post_time":"2020-03-12 09:37:56","thumbnail":{"src":"https://cdn.clien.net/web/api/file/F01/9737427/1aa3ce4df67bd9.jpg?w=780&h=30000&gif=true","size":{"width":780,"height":585}}},{"src":"https://www.clien.net/service/board/park/14700837?type=recommend","title":"비누로 30초간 손 씻으라는 이유.jpg","view_num":6269,"comment_num":28,"post_time":"2020-03-12 11:05:43","thumbnail":{"src":"https://cdn.clien.net/web/api/file/F01/9737887/1aa8c777f2e80b.jpeg?w=780&h=30000","size":{"width":700,"height":451}}},{"src":"https://www.clien.net/service/board/park/14700050?type=recommend","title":"ㅇㅇ시장이 지금까지 한 일 요약.jpg","view_num":6508,"comment_num":15,"post_time":"2020-03-12 08:12:49","thumbnail":{"src":"https://cdn.clien.net/web/api/file/F01/9737126/1a9f47edca84c4.jpeg?w=780&h=30000","size":{"width":728,"height":770}}},{"src":"https://www.clien.net/service/board/park/14700854?type=recommend","title":"펌) 대한민국 기자들의 절대 성역.jpg","view_num":6036,"comment_num":17,"post_time":"2020-03-12 11:08:11","thumbnail":{"src":"https://cdn.clien.net/web/api/file/F01/9737891/1aa8bda3299ed9.jpg?w=780&h=30000","size":{"width":750,"height":1037}}},{"src":"https://www.clien.net/service/board/park/14699805?type=recommend","title":"손정의가 난 사람은 난 사람이에요.jpg","view_num":14215,"comment_num":6,"post_time":"2020-03-12 04:09:10","thumbnail":{"src":"https://cdn.clien.net/web/api/file/F01/9736860/1a91dc42b5baa9.jpeg?w=780&h=30000","size":{"width":780,"height":1206}}},{"src":"https://www.clien.net/service/board/park/14700736?type=recommend","title":"현재 감자 하나 발령된 강원도청 상황 .TWT","view_num":4354,"comment_num":27,"post_time":"2020-03-12 10:49:09","thumbnail":{"src":"https://cdn.clien.net/web/api/file/F01/9737792/1aa7c4dc9d7bb1.png?w=780&h=30000&gif=true","size":{"width":780,"height":636}}},{"src":"https://www.clien.net/service/board/park/14699885?type=recommend","title":"팬데믹이라도 질본의 노력이 의미가 있는 이유","view_num":7724,"comment_num":7,"post_time":"2020-03-12 06:50:28","thumbnail":null},{"src":"https://www.clien.net/service/board/park/14700565?type=recommend","title":"[속보] 트럼프 \"한국 코로나19 상황 개선…여행제한 재평가\"","view_num":6009,"comment_num":15,"post_time":"2020-03-12 10:20:47","thumbnail":null},{"src":"https://www.clien.net/service/board/park/14699966?type=recommend","title":"리버풀 탈락 확정이네요.","view_num":5905,"comment_num":16,"post_time":"2020-03-12 07:34:24","thumbnail":{"src":"https://cdn.clien.net/web/api/file/F01/9737032/1a9d3de2c1c378.jpg?w=780&h=30000","size":{"width":458,"height":321}}},{"src":"https://www.clien.net/service/board/park/14699865?type=recommend","title":"코로나19 확산에 가장 기여(?)한 인간","view_num":8285,"comment_num":6,"post_time":"2020-03-12 06:19:49","thumbnail":{"src":"https://cdn.clien.net/web/api/file/F01/9736933/1a990078a6f7e9.jpg?w=780&h=30000","size":{"width":0,"height":0}}},{"src":"https://www.clien.net/service/board/park/14700118?type=recommend","title":"한국 걱정하는 외쿡친구 대응하기","view_num":5959,"comment_num":12,"post_time":"2020-03-12 08:36:59","thumbnail":null},{"src":"https://www.clien.net/service/board/park/14700030?type=recommend","title":"노통을 언급한 질본 공무원","view_num":6738,"comment_num":8,"post_time":"2020-03-12 08:01:00","thumbnail":{"src":"https://cdn.clien.net/web/api/file/F01/9737081/1a9e835225fa18.jpg?w=780&h=30000","size":{"width":640,"height":304}}},{"src":"https://www.clien.net/service/board/park/14700776?type=recommend","title":"정부 욕하던 친구들이 요즘 아닥했어요ㅋㅋ","view_num":4378,"comment_num":19,"post_time":"2020-03-12 10:55:38","thumbnail":null},{"src":"https://www.clien.net/service/board/park/14699880?type=recommend","title":"오늘은 금태섭이 발표날 입니다..","view_num":5812,"comment_num":11,"post_time":"2020-03-12 06:37:35","thumbnail":null},{"src":"https://www.clien.net/service/board/park/14700580?type=recommend","title":"'코리아 상찬회' 돼버린 美 '코로나 청문회'","view_num":4612,"comment_num":17,"post_time":"2020-03-12 10:23:06","thumbnail":null},{"src":"https://www.clien.net/service/board/park/14700122?type=recommend","title":"[단독]신천지 위장단체 간부, 대구시장 선거때 부인 보좌 의혹","view_num":4628,"comment_num":15,"post_time":"2020-03-12 08:38:09","thumbnail":null},{"src":"https://www.clien.net/service/board/park/14700114?type=recommend","title":"인스타 호러물 사진들 (혐주의)","view_num":7263,"comment_num":10,"post_time":"2020-03-12 08:35:01","thumbnail":{"src":"https://cdn.clien.net/web/api/file/F01/9737079/1a9e68e942668f.jpg?w=780&h=30000&gif=true","size":{"width":780,"height":585}}},{"src":"https://www.clien.net/service/board/park/14699911?type=recommend","title":"해외 주식 계좌 열었다가...132% 수익률!","view_num":11693,"comment_num":12,"post_time":"2020-03-12 07:06:58","thumbnail":null},{"src":"https://www.clien.net/service/board/park/14700761?type=recommend","title":"미 하원 의원, '나도 한국에 가고싶다!'","view_num":4783,"comment_num":12,"post_time":"2020-03-12 10:53:42","thumbnail":{"src":"https://cdn.clien.net/web/api/file/F01/9737796/1aa7d61eb64c4a.png?w=780&h=30000&gif=true","size":{"width":693,"height":300}}},{"src":"https://www.clien.net/service/board/park/14699968?type=recommend","title":"유재석도 울고 나도 울고 ㅠㅠ","view_num":4944,"comment_num":11,"post_time":"2020-03-12 07:35:52","thumbnail":null},{"src":"https://www.clien.net/service/board/park/14700948?type=recommend","title":"마스크 대란, 대통령이 이리 뿔난건 처음","view_num":4982,"comment_num":7,"post_time":"2020-03-12 11:27:21","thumbnail":{"src":"https://cdn.clien.net/web/api/file/F01/9738079/1aaa520d64b5f6.png?w=780&h=30000&gif=true","size":{"width":259,"height":285}}},{"src":"https://www.clien.net/service/board/lecture/14699710?type=recommend","title":"PC/모바일","view_num":2790,"comment_num":5,"post_time":"2020-03-12 02:05:04","thumbnail":{"src":"https://k.kakaocdn.net/dn/mSpZA/btqCD9szskI/EDYyhc7hyhHbRrLiyCMPjk/img.jpg","size":{"width":1125,"height":1987}}},{"src":"https://www.clien.net/service/board/news/14700009?type=recommend","title":"LG디스플레이, 스마트폰 OLED 점유율 10% 첫 돌파","view_num":4482,"comment_num":4,"post_time":"2020-03-12 07:54:07","thumbnail":null},{"src":"https://www.clien.net/service/board/park/14700072?type=recommend","title":"'민주당 공천' 정청래 심경글..'문재인 정부 성공을 위하여'","view_num":4658,"comment_num":5,"post_time":"2020-03-12 08:18:52","thumbnail":null},{"src":"https://www.clien.net/service/board/park/14699926?type=recommend","title":"뉴스공장 대만 마스크 정책 칭송하던 조중동 이틀만에.말바꿔","view_num":4618,"comment_num":5,"post_time":"2020-03-12 07:18:27","thumbnail":null}]