[{"src":"http://www.slrclub.com/bbs/vx2.php?id=best_article&category=1&no=323865","title":"주식관련 가슴아픈","view_num":6018,"comment_num":32,"post_time":"2020-03-24 14:40:48","thumbnail":{"src":"http://media.slrclub.com/2003/24/s0MDS34ed9n8pajst4.jpeg","size":{"width":430,"height":560}}},{"src":"http://www.slrclub.com/bbs/vx2.php?id=best_article&category=1&no=323864","title":"아마존 배송 근황.jpg","view_num":5684,"comment_num":41,"post_time":"2020-03-24 15:51:44","thumbnail":{"src":"http://media.slrclub.com/2003/24/s04PD69ed9ohnl36j2.jpg","size":{"width":1024,"height":768}}},{"src":"http://www.slrclub.com/bbs/vx2.php?id=best_article&category=1&no=323862","title":"대단한 31번 확진자 ㄷㄷㄷㄷㄷㄷㄷㄷㄷㄷ","view_num":9694,"comment_num":60,"post_time":"2020-03-24 15:41:00","thumbnail":{"src":"http://media.slrclub.com/2003/24/s0qZE411e45ka7evna.jpg","size":{"width":1080,"height":478}}},{"src":"http://www.slrclub.com/bbs/vx2.php?id=best_article&category=1&no=323861","title":"조권 전역","view_num":10831,"comment_num":60,"post_time":"2020-03-24 14:56:14","thumbnail":{"src":"http://media.slrclub.com/2003/24/s035h67ed9n3diu3pe.jpg","size":{"width":1365,"height":2048}}},{"src":"http://www.slrclub.com/bbs/vx2.php?id=best_article&category=1&no=323860","title":"넷플릭스 통해서 꼭 만들어졌으면 하는 우리나라 작품","view_num":8376,"comment_num":53,"post_time":"2020-03-24 14:34:07","thumbnail":{"src":"http://media.slrclub.com/2003/24/s0FIM95ed9mlp2v9mf.jpg","size":{"width":480,"height":714}}},{"src":"http://www.slrclub.com/bbs/vx2.php?id=best_article&category=1&no=323859","title":"사탄도 울고갈 보험사.jpg","view_num":12327,"comment_num":99,"post_time":"2020-03-24 14:46:01","thumbnail":{"src":"http://media.slrclub.com/2003/24/s07Jze17ed9mu05utj3.jpg","size":{"width":420,"height":708}}},{"src":"http://www.slrclub.com/bbs/vx2.php?id=best_article&category=1&no=323858","title":"민경욱 공천 확정 ㄷㄷㄷ","view_num":9334,"comment_num":59,"post_time":"2020-03-24 14:27:46","thumbnail":{"src":"http://media.slrclub.com/2003/24/s01AFO54ed9mjhmnn9c.jpg","size":{"width":680,"height":454}}},{"src":"http://www.slrclub.com/bbs/vx2.php?id=best_article&category=1&no=323857","title":"방금 여자 알바 후기","view_num":14768,"comment_num":53,"post_time":"2020-03-24 14:25:13","thumbnail":{"src":"http://media.slrclub.com/2003/24/s01942ed9ilfmpom7.jpg","size":{"width":1396,"height":1455}}},{"src":"http://www.slrclub.com/bbs/vx2.php?id=best_article&category=1&no=323856","title":"뉴욕을 못가","view_num":9746,"comment_num":34,"post_time":"2020-03-24 12:31:54","thumbnail":{"src":"http://media.slrclub.com/2003/24/s0eKA97ed9krmimflk.jpeg","size":{"width":800,"height":600}}},{"src":"http://www.slrclub.com/bbs/vx2.php?id=best_article&category=1&no=323855","title":"호불호 (有)","view_num":10402,"comment_num":50,"post_time":"2020-03-24 14:11:27","thumbnail":{"src":"http://media.slrclub.com/2003/24/s075gF20ed9m9nqeri7.png","size":{"width":628,"height":264}}},{"src":"http://www.slrclub.com/bbs/vx2.php?id=best_article&category=1&no=323851","title":"'박사방' 입장료 낸 명단 경찰 신상확인중","view_num":7608,"comment_num":60,"post_time":"2020-03-24 14:06:26","thumbnail":{"src":"http://media.slrclub.com/2003/24/s06ADT74ed9mlg5emo7.jpg","size":{"width":1201,"height":672}}},{"src":"http://www.slrclub.com/bbs/vx2.php?id=best_article&category=1&no=323850","title":"저 귀촌합니다. 말리지마세요.","view_num":7537,"comment_num":57,"post_time":"2020-03-24 13:59:20","thumbnail":{"src":"http://media.slrclub.com/2003/24/s0Y5c82ed9mgvulbnl.jpg","size":{"width":1400,"height":773}}},{"src":"http://www.slrclub.com/bbs/vx2.php?id=best_article&category=1&no=323849","title":"코로나가 행복한 벨기에 학생들","view_num":11722,"comment_num":55,"post_time":"2020-03-24 13:45:23","thumbnail":{"src":"http://media.slrclub.com/2003/24/s031o165ed9lr5rl08f.jpeg","size":{"width":900,"height":880}}},{"src":"http://www.slrclub.com/bbs/vx2.php?id=best_article&category=1&no=323848","title":"관리대상 게시물 : 우와 이정도면 거의 종교 수준이네유 ㄷㄷㄷㄷ","view_num":14623,"comment_num":68,"post_time":"2020-03-24 13:31:34","thumbnail":{"src":"http://www.slrclub.com/bbs/brimg/rpt_info_txt1.gif","size":{"width":362,"height":17}}},{"src":"http://www.slrclub.com/bbs/vx2.php?id=best_article&category=1&no=323847","title":"48세녀","view_num":19057,"comment_num":65,"post_time":"2020-03-24 13:15:02","thumbnail":{"src":"http://media.slrclub.com/2003/24/s04c4A46ed9l9svlfkl.jpg","size":{"width":600,"height":600}}},{"src":"http://www.slrclub.com/bbs/vx2.php?id=best_article&category=1&no=323846","title":"[속보] n번방 전 운영자 와치맨 징역 3년 6개월 구형","view_num":9373,"comment_num":48,"post_time":"2020-03-24 12:46:53","thumbnail":{"src":"http://file.media.slrclub.com/2003/24/s03QxE40ed9l7srm8gq.gif","size":{"width":245,"height":243}}},{"src":"http://www.slrclub.com/bbs/vx2.php?id=best_article&category=1&no=323845","title":"우울한 30대","view_num":12705,"comment_num":42,"post_time":"2020-03-24 12:02:24","thumbnail":{"src":"http://media.slrclub.com/2003/24/s01zx457ed9kebnphik.jpg","size":{"width":750,"height":1334}}},{"src":"http://www.slrclub.com/bbs/vx2.php?id=best_article&category=1&no=323844","title":"관리대상 게시물 : 그냥 개인적으로 이형이 다음 대통령 되면 좋겠습니다.","view_num":8448,"comment_num":53,"post_time":"2020-03-24 12:45:35","thumbnail":{"src":"http://www.slrclub.com/bbs/brimg/rpt_info_txt1.gif","size":{"width":362,"height":17}}},{"src":"http://www.slrclub.com/bbs/vx2.php?id=best_article&category=1&no=323843","title":"[속보] 文 \"4대 보험료 전기료 등 공과금 유예 조치","view_num":10584,"comment_num":58,"post_time":"2020-03-24 12:15:54","thumbnail":{"src":"http://media.slrclub.com/2003/24/s035h62ed9km7n9naa.jpg","size":{"width":1280,"height":720}}},{"src":"http://www.slrclub.com/bbs/vx2.php?id=best_article&category=1&no=323842","title":"속보) 생활지원비 외국민도 모두 지급","view_num":10797,"comment_num":54,"post_time":"2020-03-24 11:10:25","thumbnail":{"src":"http://media.slrclub.com/2003/24/s21990ed9j24514r2.jpg","size":{"width":1400,"height":1050}}}]